modelBLfunk.py
model_Excel.py
model_cvx.py
model_doable.py
model_dynare.py
model_financial_stability.py
model_ifrs9.py
model_latex.py
model_latex_class.py
model_run_numba.py
modelclass.py
modelclass2.py
modelconstruct.py
modeldash.py
modeldashboot.py
modeldashsidebar.py
modeldekom.py
modeldiff.py
modeldisplay.py
modelestimation.py
modelfeedback.py
modelgrab.py
modelgrabwf2.py
modelhelp.py
modelinvert.py
modeljupyter.py
modeljupytermagic.py
modelmacrograb.py
modelmanipulation.py
modelmf.py
modelnet.py
modelnewton.py
modelnormalize.py
modelpattern.py
modelpatternrev.py
modelreport.py
modelsandbox.py
modelsandbox_Mixin.py
modeltodo.py
modeluserfunk.py
modeluserfunk_old.py
modelvis.py
modelwidget.py
modelwidget_input.py
modelwidget_shinypy.py
modelflowib-2.63.dist-info/METADATA
modelflowib-2.63.dist-info/WHEEL
modelflowib-2.63.dist-info/top_level.txt
modelflowib-2.63.dist-info/RECORD
